{
  "attempt": 1,
  "status": "FAIL",
  "started_at": "2026-02-24T21:52:41.174Z",
  "finished_at": "2026-02-24T21:52:41.311Z",
  "agent": "prose-quality-auditor",
  "prompt_sha256": null,
  "invocation_ids": [],
  "required_outputs": [
    "{artifact_path}/research/PROSE-QUALITY-AUDIT.md",
    "{artifact_path}/PROSE-QUALITY-AUDIT.md"
  ],
  "artifacts": [
    {
      "path": "{artifact_path}/research/PROSE-QUALITY-AUDIT.md",
      "absolute_path": "/Users/lem/Desktop/Projects/Dev/apps/esy/client/esy.com/src/app/essays/science/lucy/research/PROSE-QUALITY-AUDIT.md",
      "sha256": "a2a268e44e614515f9ebd700273169f4d06d1e7a1e1859a847753dc730c647d7",
      "exists": true
    }
  ],
  "validations": [
    {
      "type": "file_exists_any_of",
      "pass": true,
      "checked": [
        {
          "path": "{artifact_path}/research/PROSE-QUALITY-AUDIT.md",
          "exists": true
        },
        {
          "path": "{artifact_path}/PROSE-QUALITY-AUDIT.md",
          "exists": false
        }
      ],
      "description": "At least one intake artifact must exist"
    },
    {
      "type": "not_contains",
      "path": "{artifact_path}/research/PROSE-QUALITY-AUDIT.md",
      "resolved_path": "/Users/lem/Desktop/Projects/Dev/apps/esy/client/esy.com/src/app/essays/science/lucy/research/PROSE-QUALITY-AUDIT.md",
      "pattern": "status: FAIL",
      "found": false,
      "severity": "error",
      "description": "Prose quality audit must not have FAIL status",
      "pass": true
    },
    {
      "type": "frontmatter_status",
      "path": "{artifact_path}/research/PROSE-QUALITY-AUDIT.md",
      "resolved_path": "/Users/lem/Desktop/Projects/Dev/apps/esy/client/esy.com/src/app/essays/science/lucy/research/PROSE-QUALITY-AUDIT.md",
      "checks": {
        "status": {
          "not": "FAIL"
        }
      },
      "fields": {},
      "severity": "error",
      "description": "Frontmatter status must not be FAIL",
      "reason": "File not found or no YAML frontmatter: /Users/lem/Desktop/Projects/Dev/apps/esy/client/esy.com/src/app/essays/science/lucy/research/PROSE-QUALITY-AUDIT.md",
      "pass": false
    },
    {
      "type": "regex_match",
      "path": "{client_component}",
      "resolved_path": "/Users/lem/Desktop/Projects/Dev/apps/esy/client/esy.com/src/app/essays/science/lucy/LucyClient.tsx",
      "regex": "(\\bdelve\\b|\\btapestry\\b|\\bunlock the secrets\\b|\\bin today's world\\b|\\blet's dive\\b|\\bfascinating journey\\b|\\bit's important to note\\b|\\bIn conclusion\\b)",
      "must_not_match": true,
      "matched": false,
      "severity": "warning",
      "description": "Client component should not contain common AI slop phrases (delve, tapestry, unlock the secrets, etc.)",
      "pass": true,
      "warning": false
    },
    {
      "type": "regex_match",
      "path": "{client_component}",
      "resolved_path": "/Users/lem/Desktop/Projects/Dev/apps/esy/client/esy.com/src/app/essays/science/lucy/LucyClient.tsx",
      "regex": "[\\u{1F300}-\\u{1F9FF}\\u{2600}-\\u{26FF}\\u{2700}-\\u{27BF}]",
      "must_not_match": true,
      "matched": false,
      "severity": "error",
      "description": "Client component must NOT contain emoji characters",
      "pass": true
    }
  ],
  "failure_reason": "Frontmatter status must not be FAIL"
}